funtts/__init__.py
funtts/config.py
funtts/factory.py
funtts/base/__init__.py
funtts/base/base.py
funtts/models/__init__.py
funtts/models/audio_segment.py
funtts/models/request_response.py
funtts/models/subtitle_maker.py
funtts/models/voice_info.py
funtts/tts/__init__.py
funtts/tts/azure/__init__.py
funtts/tts/azure/tts.py
funtts/tts/bark/__init__.py
funtts/tts/bark/tts.py
funtts/tts/coqui/__init__.py
funtts/tts/coqui/tts.py
funtts/tts/edge/__init__.py
funtts/tts/edge/tts.py
funtts/tts/espeak/__init__.py
funtts/tts/espeak/tts.py
funtts/tts/indextts2/__init__.py
funtts/tts/indextts2/tts.py
funtts/tts/kitten/__init__.py
funtts/tts/kitten/tts.py
funtts/tts/pyttsx3/__init__.py
funtts/tts/pyttsx3/tts.py
funtts/tts/tortoise/__init__.py
funtts/tts/tortoise/tts.py
funtts/utils/__init__.py
funtts/utils/audio_utils.py
funtts/utils/response_utils.py
funtts/utils/subtitle_utils.py
funtts_plus-0.1.11.dist-info/METADATA
funtts_plus-0.1.11.dist-info/WHEEL
funtts_plus-0.1.11.dist-info/entry_points.txt
funtts_plus-0.1.11.dist-info/top_level.txt
funtts_plus-0.1.11.dist-info/RECORD
