Metadata-Version: 2.4
Name: funtts-plus
Version: 0.1.11
Summary: 统一的文本转语音(TTS)工具库，支持多种开源TTS引擎和字幕格式
Author-email: 牛哥 <niuliangtao@qq.com>, farfarfun <farfarfun@qq.com>
Maintainer-email: 牛哥 <niuliangtao@qq.com>, farfarfun <farfarfun@qq.com>
License: MIT
Project-URL: Organization, https://github.com/farfarfun
Project-URL: Repository, https://github.com/farfarfun/funtts
Project-URL: Releases, https://github.com/farfarfun/funtts/releases
Keywords: tts,text-to-speech,audio,subtitle,speech-synthesis
Classifier: Development Status :: 4 - Beta
Classifier: Intended Audience :: Developers
Classifier: License :: OSI Approved :: MIT License
Classifier: Programming Language :: Python :: 3
Classifier: Programming Language :: Python :: 3.8
Classifier: Programming Language :: Python :: 3.9
Classifier: Programming Language :: Python :: 3.10
Classifier: Programming Language :: Python :: 3.11
Classifier: Programming Language :: Python :: 3.12
Classifier: Topic :: Multimedia :: Sound/Audio :: Speech
Classifier: Topic :: Software Development :: Libraries :: Python Modules
Requires-Python: >=3.8
Requires-Dist: funutil>=0.1.0
Requires-Dist: pydub>=0.25.0
Requires-Dist: ffmpeg-python>=0.2.0
Provides-Extra: edge
Requires-Dist: edge-tts>=6.1.0; extra == "edge"
Provides-Extra: azure
Requires-Dist: azure-cognitiveservices-speech>=1.30.0; extra == "azure"
Provides-Extra: bark
Requires-Dist: bark>=0.1.5; extra == "bark"
Requires-Dist: torch>=1.9.0; extra == "bark"
Requires-Dist: torchaudio>=0.9.0; extra == "bark"
Requires-Dist: scipy>=1.7.0; extra == "bark"
Requires-Dist: soundfile>=0.10.0; extra == "bark"
Requires-Dist: numpy>=1.20.0; extra == "bark"
Provides-Extra: tortoise
Requires-Dist: tortoise-tts>=2.4.0; extra == "tortoise"
Requires-Dist: torch>=1.9.0; extra == "tortoise"
Requires-Dist: torchaudio>=0.9.0; extra == "tortoise"
Requires-Dist: soundfile>=0.10.0; extra == "tortoise"
Requires-Dist: numpy>=1.20.0; extra == "tortoise"
Provides-Extra: indextts2
Requires-Dist: torch>=1.9.0; extra == "indextts2"
Requires-Dist: torchaudio>=0.9.0; extra == "indextts2"
Requires-Dist: transformers>=4.20.0; extra == "indextts2"
Requires-Dist: soundfile>=0.10.0; extra == "indextts2"
Requires-Dist: numpy>=1.20.0; extra == "indextts2"
Provides-Extra: kitten
Requires-Dist: torch>=1.9.0; extra == "kitten"
Requires-Dist: torchaudio>=0.9.0; extra == "kitten"
Requires-Dist: soundfile>=0.10.0; extra == "kitten"
Requires-Dist: numpy>=1.20.0; extra == "kitten"
Provides-Extra: espeak
Provides-Extra: pyttsx3
Requires-Dist: pyttsx3>=2.90; extra == "pyttsx3"
Provides-Extra: all
Requires-Dist: funtts-plus[azure,bark,edge,espeak,indextts2,kitten,pyttsx3,tortoise]; extra == "all"
